setup.py
cdep_base/__init__.py
cdep_base.egg-info/PKG-INFO
cdep_base.egg-info/SOURCES.txt
cdep_base.egg-info/dependency_links.txt
cdep_base.egg-info/requires.txt
cdep_base.egg-info/top_level.txt
cdep_base/configuration/__init__.py
cdep_base/configuration/classes/__init__.py
cdep_base/configuration/classes/configuration.py